fivenines_agent/__main__.py
fivenines_agent/agent.py
fivenines_agent/cpu.py
fivenines_agent/disks.py
fivenines_agent/env.py
fivenines_agent/files.py
fivenines_agent/ip.py
fivenines_agent/network.py
fivenines_agent/nginx.py
fivenines_agent/partitions.py
fivenines_agent/processes.py
fivenines_agent/redis.py
fivenines_agent/synchronization_queue.py
fivenines_agent/synchronizer.py
fivenines_agent-1.0.5.dist-info/LICENSE
fivenines_agent-1.0.5.dist-info/METADATA
fivenines_agent-1.0.5.dist-info/WHEEL
fivenines_agent-1.0.5.dist-info/entry_points.txt
fivenines_agent-1.0.5.dist-info/RECORD
